{
  "id": "58960",
  "name": "Yo-Yo Ma",
  "popularity": 45,
  "followers": {
    "total": 450882
  },
  "genres": [
    "classical"
  ],
  "images": [
    {
      "url": "https://cdn-images.dzcdn.net/images/artist/98feb07cbd68e42a0bd92b0a4b611f69/1000x1000-000000-80-0-0.jpg",
      "height": 1000,
      "width": 1000
    },
    {
      "url": "https://cdn-images.dzcdn.net/images/artist/98feb07cbd68e42a0bd92b0a4b611f69/500x500-000000-80-0-0.jpg",
      "height": 500,
      "width": 500
    },
    {
      "url": "https://cdn-images.dzcdn.net/images/artist/98feb07cbd68e42a0bd92b0a4b611f69/250x250-000000-80-0-0.jpg",
      "height": 250,
      "width": 250
    }
  ],
  "external_urls": {
    "spotify": "https://www.deezer.com/artist/58960"
  },
  "uri": "deezer:artist:58960"
}